pyeaze/__init__.py
pyeaze/pyeaze.py
pyeaze-0.8.1.dist-info/LICENSE
pyeaze-0.8.1.dist-info/METADATA
pyeaze-0.8.1.dist-info/WHEEL
pyeaze-0.8.1.dist-info/top_level.txt
pyeaze-0.8.1.dist-info/RECORD
