Metadata-Version: 2.1
Name: pyeaze
Version: 0.8.1
Summary: A package for animating values with easing functions
Author: Vasigaran
Author-email: vasigaranvip195@gmail.com
Keywords: python,animation,animate,ease,easing,motion
Classifier: Development Status :: 1 - Planning
Classifier: Intended Audience :: Developers
Classifier: Programming Language :: Python :: 3
Classifier: Programming Language :: Python :: 3.10
License-File: LICENSE
Requires-Dist: scipy
Requires-Dist: numpy
